queuack/__init__.py
queuack/core.py
queuack/dag.py
queuack/data_models.py
queuack/job_store.py
queuack/status.py
queuack-0.1.2.dist-info/licenses/LICENSE
queuack-0.1.2.dist-info/METADATA
queuack-0.1.2.dist-info/WHEEL
queuack-0.1.2.dist-info/top_level.txt
queuack-0.1.2.dist-info/RECORD
