Metadata-Version: 2.4
Name: queuack
Version: 0.1.2
Summary: A DuckDB-based queue manager
Requires-Python: >=3.9
License-File: LICENSE
Requires-Dist: duckdb>=1.4.1
Requires-Dist: networkx>=3.2.1
Requires-Dist: cloudpickle>=3.1.1
Dynamic: license-file
